leetehao
