Metadata-Version: 1.1
Name: leetehao
Version: 0.1.1
Summary: En/decoder for: leet, morse, roman
Home-page: https://github.com/myyang/leetehao
Author: Garfield
Author-email: ymy1019@gmail.com
License: BSD
Keywords: leetehao
Platform: UNKNOWN
Classifier: License :: OSI Approved :: BSD License
Classifier: Programming Language :: Python :: 2
Classifier: Programming Language :: Python :: 2.6
Classifier: Programming Language :: Python :: 2.7
Classifier: Programming Language :: Python :: 3
Classifier: Programming Language :: Python :: 3.3
Classifier: Programming Language :: Python :: 3.4
